sharepointsimple/__init__.py
sharepointsimple/sharepointsimple.py
sharepointsimple-0.1.5.dist-info/LICENSE
sharepointsimple-0.1.5.dist-info/METADATA
sharepointsimple-0.1.5.dist-info/WHEEL
sharepointsimple-0.1.5.dist-info/top_level.txt
sharepointsimple-0.1.5.dist-info/RECORD
