Metadata-Version: 2.1
Name: sharepointsimple
Version: 0.1.5
Summary: sharepointsimple is a python library to upload and download the files from SharePoint
Home-page: UNKNOWN
Author: Harish Kumar V
Author-email: <vharishkumar21@gmail.com>
License: MIT
Keywords: python,sharepoint,SharePoint,Sharepoint,sharepoint api
Platform: UNKNOWN
Classifier: Development Status :: 5 - Production/Stable
Classifier: Intended Audience :: Developers
Classifier: Programming Language :: Python :: 3
Classifier: License :: OSI Approved :: MIT License
Classifier: Operating System :: OS Independent
Requires-Dist: requests
